{
    "loss": [
        {
            "min": 0.0,
            "max": 1027.9884033203125,
            "mean": 61.37216567993164,
            "std": 94.5462417602539
        },
        {
            "min": 0.0,
            "max": 567.0462646484375,
            "mean": 53.801517486572266,
            "std": 73.2205581665039
        },
        {
            "min": 0.0,
            "max": 474.77777099609375,
            "mean": 44.800743103027344,
            "std": 70.68803405761719
        },
        {
            "min": 0.0,
            "max": 654.6753540039062,
            "mean": 43.390071868896484,
            "std": 68.04950714111328
        },
        {
            "min": 0.0,
            "max": 780.2491455078125,
            "mean": 52.67799377441406,
            "std": 78.40548706054688
        },
        {
            "min": 0.0,
            "max": 1346.8189697265625,
            "mean": 177.30250549316406,
            "std": 153.07196044921875
        },
        {
            "min": 0.0,
            "max": 862.0709838867188,
            "mean": 83.28282928466797,
            "std": 78.64156341552734
        },
        {
            "min": 0.0,
            "max": 906.888671875,
            "mean": 69.52027130126953,
            "std": 76.61213684082031
        },
        {
            "min": 0.0,
            "max": 785.2930908203125,
            "mean": 65.37419891357422,
            "std": 74.84186553955078
        },
        {
            "min": 0.0,
            "max": 585.4729614257812,
            "mean": 55.08103561401367,
            "std": 54.92593002319336
        },
        {
            "min": 0.0,
            "max": 789.4359130859375,
            "mean": 81.7900161743164,
            "std": 72.93771362304688
        },
        {
            "min": 0.0,
            "max": 358.7689514160156,
            "mean": 57.113277435302734,
            "std": 42.070030212402344
        },
        {
            "min": 0.0,
            "max": 410.6100769042969,
            "mean": 69.5531997680664,
            "std": 49.24424362182617
        },
        {
            "min": 0.0,
            "max": 502.3084716796875,
            "mean": 84.85781860351562,
            "std": 59.52981948852539
        },
        {
            "min": 0.0,
            "max": 530.5728149414062,
            "mean": 91.38355255126953,
            "std": 65.64574432373047
        },
        {
            "min": 0.0,
            "max": 273.873779296875,
            "mean": 48.772621154785156,
            "std": 33.91387176513672
        },
        {
            "min": 0.0,
            "max": 207.70132446289062,
            "mean": 32.66816711425781,
            "std": 21.86846351623535
        },
        {
            "min": 0.0,
            "max": 446.5019836425781,
            "mean": 33.76521301269531,
            "std": 25.88013458251953
        },
        {
            "min": 0.0,
            "max": 294.2002258300781,
            "mean": 36.54905700683594,
            "std": 28.94743537902832
        },
        {
            "min": 0.0,
            "max": 261.87786865234375,
            "mean": 36.41920471191406,
            "std": 28.33160400390625
        },
        {
            "min": 0.0,
            "max": 397.6319885253906,
            "mean": 53.38233947753906,
            "std": 39.4391975402832
        },
        {
            "min": 0.0,
            "max": 331.5062561035156,
            "mean": 47.922462463378906,
            "std": 37.40106201171875
        },
        {
            "min": 0.0,
            "max": 304.9224853515625,
            "mean": 45.64653396606445,
            "std": 34.62837600708008
        },
        {
            "min": 0.0,
            "max": 316.16314697265625,
            "mean": 42.99385070800781,
            "std": 32.14142608642578
        },
        {
            "min": 0.0,
            "max": 299.032470703125,
            "mean": 48.58134460449219,
            "std": 37.24115753173828
        },
        {
            "min": 0.0,
            "max": 443.06524658203125,
            "mean": 58.2839241027832,
            "std": 43.691917419433594
        },
        {
            "min": 0.0,
            "max": 370.2544250488281,
            "mean": 55.643516540527344,
            "std": 44.49964141845703
        },
        {
            "min": 0.0,
            "max": 514.90869140625,
            "mean": 52.03215026855469,
            "std": 41.5661506652832
        },
        {
            "min": 0.0,
            "max": 315.29339599609375,
            "mean": 52.58407974243164,
            "std": 41.019134521484375
        },
        {
            "min": 0.0,
            "max": 365.39373779296875,
            "mean": 52.45426940917969,
            "std": 41.4730224609375
        },
        {
            "min": 0.0,
            "max": 327.0694885253906,
            "mean": 43.892791748046875,
            "std": 36.1295280456543
        },
        {
            "min": 0.0,
            "max": 337.9857482910156,
            "mean": 43.36442565917969,
            "std": 38.740814208984375
        },
        {
            "min": 0.0,
            "max": 411.2861328125,
            "mean": 42.843406677246094,
            "std": 37.860111236572266
        },
        {
            "min": 0.0,
            "max": 389.6401672363281,
            "mean": 46.27737045288086,
            "std": 44.212074279785156
        },
        {
            "min": 0.0,
            "max": 476.866455078125,
            "mean": 49.81822204589844,
            "std": 46.4769287109375
        },
        {
            "min": 0.0,
            "max": 407.9501953125,
            "mean": 54.12531661987305,
            "std": 40.77716064453125
        },
        {
            "min": 0.0,
            "max": 300.8373107910156,
            "mean": 47.621238708496094,
            "std": 36.92314910888672
        },
        {
            "min": 0.0,
            "max": 490.001708984375,
            "mean": 52.30815124511719,
            "std": 44.4338493347168
        },
        {
            "min": 0.0,
            "max": 522.6238403320312,
            "mean": 58.14373779296875,
            "std": 48.38505935668945
        },
        {
            "min": 0.0,
            "max": 418.1852722167969,
            "mean": 54.95111083984375,
            "std": 45.1087532043457
        },
        {
            "min": 0.0,
            "max": 311.994384765625,
            "mean": 44.37191390991211,
            "std": 36.01298141479492
        },
        {
            "min": 0.0,
            "max": 331.2278137207031,
            "mean": 42.488807678222656,
            "std": 37.75662612915039
        },
        {
            "min": 0.0,
            "max": 317.90899658203125,
            "mean": 43.263633728027344,
            "std": 38.89949417114258
        },
        {
            "min": 0.0,
            "max": 290.156494140625,
            "mean": 44.110286712646484,
            "std": 39.70589828491211
        },
        {
            "min": 0.0,
            "max": 276.0183410644531,
            "mean": 47.98929977416992,
            "std": 40.7783317565918
        },
        {
            "min": 0.0,
            "max": 382.2452087402344,
            "mean": 55.805240631103516,
            "std": 40.32569122314453
        },
        {
            "min": 0.0,
            "max": 397.599609375,
            "mean": 56.9622917175293,
            "std": 45.41437911987305
        },
        {
            "min": 0.0,
            "max": 510.9013366699219,
            "mean": 54.581974029541016,
            "std": 42.50811004638672
        },
        {
            "min": 0.0,
            "max": 379.63848876953125,
            "mean": 54.81584930419922,
            "std": 42.58636474609375
        },
        {
            "min": 0.0,
            "max": 391.6180725097656,
            "mean": 54.54719924926758,
            "std": 42.9996452331543
        }
    ],
    "train_scores": [
        {
            "min": -380.0,
            "max": 95.0,
            "mean": -91.34336853027344,
            "std": 179.20298767089844
        },
        {
            "min": -365.0,
            "max": 95.0,
            "mean": -46.47979736328125,
            "std": 158.44923400878906
        },
        {
            "min": -340.0,
            "max": 95.0,
            "mean": -30.198156356811523,
            "std": 153.1831512451172
        },
        {
            "min": -330.0,
            "max": 95.0,
            "mean": -22.026201248168945,
            "std": 146.36639404296875
        },
        {
            "min": -350.0,
            "max": 95.0,
            "mean": -23.07111167907715,
            "std": 149.03469848632812
        },
        {
            "min": -375.0,
            "max": 95.0,
            "mean": 28.06389045715332,
            "std": 108.4870376586914
        },
        {
            "min": -330.0,
            "max": 95.0,
            "mean": 26.877906799316406,
            "std": 110.83203887939453
        },
        {
            "min": -330.0,
            "max": 95.0,
            "mean": 14.485437393188477,
            "std": 126.14456939697266
        },
        {
            "min": -330.0,
            "max": 95.0,
            "mean": 0.5441176295280457,
            "std": 138.58572387695312
        },
        {
            "min": -335.0,
            "max": 95.0,
            "mean": 23.261905670166016,
            "std": 120.90538024902344
        },
        {
            "min": -310.0,
            "max": 95.0,
            "mean": 70.97167205810547,
            "std": 35.33008575439453
        },
        {
            "min": -305.0,
            "max": 95.0,
            "mean": 69.75035858154297,
            "std": 27.891925811767578
        },
        {
            "min": -320.0,
            "max": 95.0,
            "mean": 67.59041595458984,
            "std": 41.095794677734375
        },
        {
            "min": -320.0,
            "max": 95.0,
            "mean": 64.16693878173828,
            "std": 57.64495849609375
        },
        {
            "min": -325.0,
            "max": 95.0,
            "mean": 66.94418334960938,
            "std": 44.13587188720703
        },
        {
            "min": -50.0,
            "max": 95.0,
            "mean": 74.49154663085938,
            "std": 17.35161018371582
        },
        {
            "min": -375.0,
            "max": 95.0,
            "mean": 73.98421478271484,
            "std": 23.37836265563965
        },
        {
            "min": -82.0,
            "max": 95.0,
            "mean": 73.65292358398438,
            "std": 18.668258666992188
        },
        {
            "min": -43.0,
            "max": 95.0,
            "mean": 74.28477478027344,
            "std": 17.4383544921875
        },
        {
            "min": -6.0,
            "max": 95.0,
            "mean": 75.1092529296875,
            "std": 15.947860717773438
        },
        {
            "min": -395.0,
            "max": 95.0,
            "mean": 74.16429901123047,
            "std": 24.11662483215332
        },
        {
            "min": -21.0,
            "max": 95.0,
            "mean": 74.72000122070312,
            "std": 15.734400749206543
        },
        {
            "min": -23.0,
            "max": 95.0,
            "mean": 74.28778076171875,
            "std": 16.78313636779785
        },
        {
            "min": -9.0,
            "max": 95.0,
            "mean": 74.7402572631836,
            "std": 15.578737258911133
        },
        {
            "min": -395.0,
            "max": 95.0,
            "mean": 72.06620788574219,
            "std": 24.490520477294922
        },
        {
            "min": -400.0,
            "max": 95.0,
            "mean": 72.8116683959961,
            "std": 27.774784088134766
        },
        {
            "min": -60.0,
            "max": 95.0,
            "mean": 73.90801239013672,
            "std": 18.026718139648438
        },
        {
            "min": -29.0,
            "max": 95.0,
            "mean": 74.55269622802734,
            "std": 16.928356170654297
        },
        {
            "min": -20.0,
            "max": 95.0,
            "mean": 74.68258666992188,
            "std": 16.570104598999023
        },
        {
            "min": -65.0,
            "max": 95.0,
            "mean": 74.8915786743164,
            "std": 17.720542907714844
        },
        {
            "min": -88.0,
            "max": 95.0,
            "mean": 73.96078491210938,
            "std": 17.866975784301758
        },
        {
            "min": -108.0,
            "max": 95.0,
            "mean": 74.38651275634766,
            "std": 17.806346893310547
        },
        {
            "min": -340.0,
            "max": 95.0,
            "mean": 72.81208038330078,
            "std": 23.65851593017578
        },
        {
            "min": -79.0,
            "max": 95.0,
            "mean": 74.89961242675781,
            "std": 16.974124908447266
        },
        {
            "min": -69.0,
            "max": 95.0,
            "mean": 74.24838256835938,
            "std": 19.42376708984375
        },
        {
            "min": -5.0,
            "max": 95.0,
            "mean": 74.358154296875,
            "std": 17.14991569519043
        },
        {
            "min": -5.0,
            "max": 95.0,
            "mean": 74.19559478759766,
            "std": 16.566238403320312
        },
        {
            "min": -12.0,
            "max": 95.0,
            "mean": 74.59382629394531,
            "std": 17.150617599487305
        },
        {
            "min": -375.0,
            "max": 95.0,
            "mean": 73.72512817382812,
            "std": 23.426532745361328
        },
        {
            "min": -305.0,
            "max": 95.0,
            "mean": 73.55099487304688,
            "std": 21.067304611206055
        },
        {
            "min": -24.0,
            "max": 95.0,
            "mean": 74.08441162109375,
            "std": 16.366792678833008
        },
        {
            "min": 1.0,
            "max": 95.0,
            "mean": 74.90827941894531,
            "std": 16.726621627807617
        },
        {
            "min": -19.0,
            "max": 95.0,
            "mean": 74.76220703125,
            "std": 16.336748123168945
        },
        {
            "min": -105.0,
            "max": 95.0,
            "mean": 74.37774658203125,
            "std": 17.91060447692871
        },
        {
            "min": -31.0,
            "max": 95.0,
            "mean": 73.96068572998047,
            "std": 16.912729263305664
        },
        {
            "min": -67.0,
            "max": 95.0,
            "mean": 74.54013061523438,
            "std": 17.737276077270508
        },
        {
            "min": -106.0,
            "max": 95.0,
            "mean": 73.02799987792969,
            "std": 21.036760330200195
        },
        {
            "min": -23.0,
            "max": 95.0,
            "mean": 73.97265625,
            "std": 17.13168716430664
        },
        {
            "min": -375.0,
            "max": 95.0,
            "mean": 73.49868774414062,
            "std": 27.036890029907227
        },
        {
            "min": -62.0,
            "max": 95.0,
            "mean": 74.42009735107422,
            "std": 17.439111709594727
        }
    ],
    "test_scores": [
        {
            "min": -360.0,
            "max": 95.0,
            "mean": -61.69,
            "std": 154.75540022887733
        },
        {
            "min": -330.0,
            "max": 95.0,
            "mean": -11.23,
            "std": 149.18732218255008
        },
        {
            "min": -325.0,
            "max": 95.0,
            "mean": -17.51,
            "std": 158.45576638292468
        },
        {
            "min": -330.0,
            "max": 95.0,
            "mean": -14.43,
            "std": 147.07877175173854
        },
        {
            "min": -350.0,
            "max": 95.0,
            "mean": -108.35,
            "std": 184.19632868219713
        },
        {
            "min": -345.0,
            "max": 95.0,
            "mean": 7.67,
            "std": 147.11023451820068
        },
        {
            "min": -320.0,
            "max": 95.0,
            "mean": -31.52,
            "std": 156.79543870916652
        },
        {
            "min": -315.0,
            "max": 95.0,
            "mean": 5.69,
            "std": 131.98891582250383
        },
        {
            "min": -330.0,
            "max": 95.0,
            "mean": 21.4,
            "std": 127.46834901260782
        },
        {
            "min": -315.0,
            "max": 95.0,
            "mean": 30.45,
            "std": 108.14364290146692
        },
        {
            "min": -340.0,
            "max": 95.0,
            "mean": 69.98,
            "std": 44.21311570111294
        },
        {
            "min": -18.0,
            "max": 95.0,
            "mean": 73.86,
            "std": 21.665188667537613
        },
        {
            "min": -69.0,
            "max": 95.0,
            "mean": 69.51,
            "std": 23.481267001590865
        },
        {
            "min": 28.0,
            "max": 95.0,
            "mean": 74.05,
            "std": 15.432028382555549
        },
        {
            "min": -320.0,
            "max": 95.0,
            "mean": 70.27,
            "std": 42.039470738818764
        },
        {
            "min": 13.0,
            "max": 95.0,
            "mean": 71.82,
            "std": 18.44797007803298
        },
        {
            "min": -17.0,
            "max": 95.0,
            "mean": 75.06,
            "std": 17.25793730432464
        },
        {
            "min": -10.0,
            "max": 95.0,
            "mean": 73.81,
            "std": 17.586184918850364
        },
        {
            "min": 21.0,
            "max": 95.0,
            "mean": 73.67,
            "std": 16.159860766726922
        },
        {
            "min": 30.0,
            "max": 95.0,
            "mean": 74.43,
            "std": 14.702554199866091
        },
        {
            "min": 11.0,
            "max": 95.0,
            "mean": 75.35,
            "std": 13.82778000982081
        },
        {
            "min": 20.0,
            "max": 95.0,
            "mean": 73.65,
            "std": 17.186259046110063
        },
        {
            "min": 23.0,
            "max": 95.0,
            "mean": 75.76,
            "std": 13.850718392920996
        },
        {
            "min": -11.0,
            "max": 95.0,
            "mean": 76.6,
            "std": 16.130096093948108
        },
        {
            "min": 18.0,
            "max": 95.0,
            "mean": 73.73,
            "std": 14.370006958940557
        },
        {
            "min": 8.0,
            "max": 95.0,
            "mean": 73.67,
            "std": 17.16802551256259
        },
        {
            "min": -45.0,
            "max": 95.0,
            "mean": 72.27,
            "std": 20.61060649277454
        },
        {
            "min": 1.0,
            "max": 95.0,
            "mean": 72.67,
            "std": 16.767262746196828
        },
        {
            "min": 1.0,
            "max": 95.0,
            "mean": 74.78,
            "std": 17.13684918530825
        },
        {
            "min": 13.0,
            "max": 95.0,
            "mean": 73.34,
            "std": 18.63449489522053
        },
        {
            "min": -320.0,
            "max": 95.0,
            "mean": 67.75,
            "std": 43.64112166294537
        },
        {
            "min": 23.0,
            "max": 95.0,
            "mean": 73.88,
            "std": 14.652153425350146
        },
        {
            "min": 18.0,
            "max": 95.0,
            "mean": 75.2,
            "std": 16.261611236282832
        },
        {
            "min": -28.0,
            "max": 95.0,
            "mean": 72.78,
            "std": 18.942850894202806
        },
        {
            "min": -16.0,
            "max": 95.0,
            "mean": 74.57,
            "std": 16.924098203449425
        },
        {
            "min": 3.0,
            "max": 95.0,
            "mean": 73.65,
            "std": 16.745372495110402
        },
        {
            "min": 26.0,
            "max": 95.0,
            "mean": 74.53,
            "std": 15.305198463267308
        },
        {
            "min": 30.0,
            "max": 95.0,
            "mean": 75.04,
            "std": 14.7172823578268
        },
        {
            "min": 3.0,
            "max": 95.0,
            "mean": 76.89,
            "std": 16.369419659841334
        },
        {
            "min": 32.0,
            "max": 95.0,
            "mean": 75.87,
            "std": 13.212611399719588
        },
        {
            "min": -18.0,
            "max": 95.0,
            "mean": 72.39,
            "std": 18.130579141329157
        },
        {
            "min": 33.0,
            "max": 95.0,
            "mean": 74.99,
            "std": 14.183437524098311
        },
        {
            "min": 3.0,
            "max": 95.0,
            "mean": 71.26,
            "std": 19.530294416623626
        },
        {
            "min": 26.0,
            "max": 95.0,
            "mean": 78.59,
            "std": 13.044611914503246
        },
        {
            "min": -22.0,
            "max": 95.0,
            "mean": 74.02,
            "std": 19.100774853392725
        },
        {
            "min": -14.0,
            "max": 95.0,
            "mean": 76.5,
            "std": 16.567739737212197
        },
        {
            "min": -19.0,
            "max": 95.0,
            "mean": 72.45,
            "std": 20.942003247063067
        },
        {
            "min": -8.0,
            "max": 95.0,
            "mean": 73.61,
            "std": 16.862321904174408
        },
        {
            "min": 11.0,
            "max": 95.0,
            "mean": 72.53,
            "std": 18.077308981150928
        },
        {
            "min": 25.0,
            "max": 95.0,
            "mean": 77.08,
            "std": 14.485634262951692
        }
    ],
    "time": [
        1.7206232031186421,
        3.3521360119183856,
        4.999326582749685,
        6.651542556285858,
        8.434721899032592,
        10.209314366181692,
        12.057770387331646,
        13.83519426981608,
        15.577340646584828,
        17.184014987945556,
        18.67354848384857,
        20.27365942398707,
        21.83034227291743,
        23.44167863925298,
        25.041395656267802,
        26.666118899981182,
        28.248533288637798,
        29.828690413633982,
        31.45555444161097,
        33.083440665404005,
        34.7071675658226,
        36.40186703999837,
        38.06756187677384,
        39.70941100915273,
        41.32297713359197,
        42.98297911485036,
        44.64573499759038,
        46.2918700615565,
        47.94201449950536,
        49.5900521159172,
        51.2354438384374,
        52.868095048268636,
        54.536430382728575,
        56.1773220539093,
        57.83911276261012,
        59.48783669869105,
        61.19312613010406,
        62.803894726435345,
        64.39740635156632,
        65.98219118118286,
        67.58768818775813,
        69.2045682946841,
        70.81784052054087,
        72.40791240930557,
        74.02227851549785,
        75.62445226113002,
        77.25028486251831,
        78.8810521443685,
        80.48335454463958,
        82.09070424636205
    ],
    "epochs": 50,
    "info": {
        "description": "",
        "resolution": [
            120,
            160
        ],
        "frame_repeat": 12,
        "learning_rate": 0.00025,
        "discount_factor": 0.99,
        "train_epochs": 50,
        "learning_steps_per_epoch": 2000,
        "replay_memory_size": 10000,
        "batch_size": 32,
        "test_episodes_per_epoch": 100,
        "net_descritpion": "None",
        "net_parameters:": 0,
        "dueling Double DQN": true,
        "net_parameters": 30711497
    }
}